certbot_dns_online/__init__.py
certbot_dns_online/dns_online.py
certbot_dns_online-0.0.8.dist-info/LICENSE.txt
certbot_dns_online-0.0.8.dist-info/METADATA
certbot_dns_online-0.0.8.dist-info/WHEEL
certbot_dns_online-0.0.8.dist-info/entry_points.txt
certbot_dns_online-0.0.8.dist-info/top_level.txt
certbot_dns_online-0.0.8.dist-info/RECORD
